those_dicts/__init__.py
those_dicts-0.1.1.dist-info/METADATA
those_dicts-0.1.1.dist-info/WHEEL
those_dicts-0.1.1.dist-info/RECORD
