Metadata-Version: 2.1
Name: those-dicts
Version: 0.1.1
Summary: Those missing flavors of dict
Home-page: https://github.com/jakubgajski/those_dicts
License: MIT
Keywords: graph,batch,two way,dict,dicts,data structures,lightweight
Author: Jakub Gajski
Author-email: jakub.gajski@gmail.com
Requires-Python: >=3.9,<4.0
Classifier: License :: OSI Approved :: MIT License
Classifier: Programming Language :: Python :: 3
Classifier: Programming Language :: Python :: 3.9
Classifier: Programming Language :: Python :: 3.10
Classifier: Programming Language :: Python :: 3.11
Classifier: Programming Language :: Python :: 3.12
Project-URL: Repository, https://github.com/jakubgajski/those_dicts
